ulianovellipse/__init__.py
ulianovellipse/ulianovellipse.py
ulianovellipse-1.8.4.dist-info/LICENSE
ulianovellipse-1.8.4.dist-info/METADATA
ulianovellipse-1.8.4.dist-info/WHEEL
ulianovellipse-1.8.4.dist-info/top_level.txt
ulianovellipse-1.8.4.dist-info/RECORD
