Metadata-Version: 2.1
Name: ulianovellipse
Version: 1.8.4
Summary: Library for handling Ulianov elliptical functions
Author: Policarpo Yoshin Ulianov
Author-email: poliyu77@gmail.com
License-File: LICENSE
Requires-Dist: numpy
